LICENSE.txt
README
setup.cfg
setup.py
loongtutwo/__init__.py
loongtutwo/prayut.py
loongtutwo.egg-info/PKG-INFO
loongtutwo.egg-info/SOURCES.txt
loongtutwo.egg-info/dependency_links.txt
loongtutwo.egg-info/top_level.txt