Metadata-Version: 2.1
Name: loongtutwo
Version: 0.0.1
Summary: Show Loong Tu Name Jaaa
Author: Makagun
License: MIT
Keywords: LOONGTU,PRAWIT,THAILAND
Classifier: Development Status :: 3 - Alpha
Classifier: Intended Audience :: Developers
Classifier: Topic :: Software Development :: Build Tools
Classifier: License :: OSI Approved :: MIT License
Classifier: Programming Language :: Python :: 3
Classifier: Programming Language :: Python :: 3.4
Classifier: Programming Language :: Python :: 3.5
Classifier: Programming Language :: Python :: 3.6
Classifier: Programming Language :: Python :: 3.7
Classifier: Programming Language :: Python :: 3.8
License-File: LICENSE.txt
